Metadata-Version: 2.1
Name: image-processing-daniel
Version: 0.0.1
Summary: NTT DATA bootcamp
Home-page: https://github.com/daniel-neves-dev/image-processing-package.git
Author: Daniel
Author-email: danielnevesoliveira052@gmail.com
License: UNKNOWN
Platform: UNKNOWN
Requires-Python: >=3.8
Requires-Dist: matplotlib (~=3.9.2)
Requires-Dist: numpy (~=2.1.2)
Requires-Dist: scikit-image (~=0.24.0)
Requires-Dist: setuptools (~=59.6.0)
